nutanix_shim_server/__init__.py
nutanix_shim_server/clustermgmt.py
nutanix_shim_server/core.py
nutanix_shim_server/networking.py
nutanix_shim_server/server.py
nutanix_shim_server/utils.py
nutanix_shim_server/vmm.py
nutanix_shim_server/routes/__init__.py
nutanix_shim_server/routes/clustermgmt.py
nutanix_shim_server/routes/networking.py
nutanix_shim_server/routes/vmm.py
nutanix_shim_server-0.1.3.dist-info/METADATA
nutanix_shim_server-0.1.3.dist-info/WHEEL
nutanix_shim_server-0.1.3.dist-info/entry_points.txt
nutanix_shim_server-0.1.3.dist-info/licenses/LICENSE
nutanix_shim_server-0.1.3.dist-info/RECORD
