Metadata-Version: 2.4
Name: nutanix-shim-server
Version: 0.1.3
Summary: Server for the Foreman Nutanix shim plugin
Author-email: Miles Granger <mgra@norceresearch.no>
License-File: LICENSE
Requires-Python: >=3.11
Requires-Dist: fastapi[standard]>=0.118.0
Requires-Dist: ntnx-clustermgmt-py-client~=4.0.0
Requires-Dist: ntnx-networking-py-client~=4.0.0
Requires-Dist: ntnx-prism-py-client~=4.0.0
Requires-Dist: ntnx-vmm-py-client~=4.0.0
